{
    "type": "palette",
    "priority": 45,
    "displayName": "text.itemswapper.palette.copper.lightning_rod",
    "items": [
        "minecraft:lightning_rod",
        "minecraft:exposed_lightning_rod",
        "minecraft:weathered_lightning_rod",
        "minecraft:oxidized_lightning_rod",
        "minecraft:waxed_lightning_rod",
        "minecraft:waxed_exposed_lightning_rod",
        "minecraft:waxed_weathered_lightning_rod",
        "minecraft:waxed_oxidized_lightning_rod"
    ],
    "shortcuts": [
        {
            "type": "link",
            "target": "itemswapper:v2/copper/copper_door"
        },
        {
            "type": "link",
            "target": "itemswapper:v2/copper/copper_trapdoor"
        },
        {
            "type": "link",
            "target": "itemswapper:v2/copper/copper_chain"
        },
        {
            "type": "link",
            "target": "itemswapper:v2/copper/copper_bars"
        },
        {
            "type": "link",
            "target": "itemswapper:v2/copper/lightning_rod"
        },
        {
            "type": "link",
            "target": "itemswapper:v2/copper/copper_lantern"
        }
    ]
}
